Workbook

Sheet Flujo 2025
B1: BENGALA AUDIOVISUAL, S.A. DE C.V. | E1: Estado Flujo de Efectivo
B2: Estados de Flujos de Efectivo | E2: Informa sobre los movimientos de efectivo y sus equivalentes
B3: Del 1 enero al 31 de Diciembre de 2025
B4: (Valores expresados en dólares de los Estados Unidos de América)
C6: 2025
B7: Flujo de efectivo por actividades de operación:
B8: Excedente (Deficit) de ingresos sobre Ejercicio 2025 | C8: -3548.1 | E8: <--- | F8: Inicia con lo que refleja el Estado de Resultado
B9: Ajustes para conciliar el excedente de ingresos sobre gastos, con el efectivo neto provisto por las operaciones:
B10: Depreciación | C10: =+'HOJA DE TRABAJO'!F5 -> 0 | E10: <--- | F10: Le sumamos el incremento de la depreciacion al resultado porque este no representa salida de dinero
B11: Retiro neto de activos | C11: ='HOJA DE TRABAJO'!F28 -> 0
B12: Movimiento en el capital de trabajo:
B13: Disminución (aumento) en cuentas por cobrar | C13: =+'HOJA DE TRABAJO'!F7 -> 721.19
B14: Disminución (aumento) en inventario | C14: =+'HOJA DE TRABAJO'!F9 -> 0
B15: Disminución (aumento) pagos anticipados | C15: =+'HOJA DE TRABAJO'!F11 -> -154.87
B16: Disminución (aumento) Iva Credito | C16: =+'HOJA DE TRABAJO'!F13 -> 768
B17: Aumento (disminución) en cuentas por pagar y gastos acumulados | C17: =+'HOJA DE TRABAJO'!F15 -> -1091.6 | F17: Le sumamos aquello que no representa salida dinero de efectivo
B18: Aumento (disminución) en en Deuda Financiera a L.P. | C18: =+'HOJA DE TRABAJO'!F18 -> 0 | F18: Restamos aquello que si representa salida de efectivo
B19: Disminución (aumento) en obligaciones a corto plazo | C19: =+'HOJA DE TRABAJO'!F20 -> 0 | F19: Estas cuentas afectaron los resultados de septiembre 2014
B20: Disminución (aumento) en Retenciones por pagar | C20: =+'HOJA DE TRABAJO'!F22 -> -102.04
B21: Aumento (disminución) Impuesto por pagar | C21: =+'HOJA DE TRABAJO'!F24 -> 154.87
B22: Obligaciones a Corto Plazo | C22: =+'HOJA DE TRABAJO'!F26 -> 0
B23: Efectivo neto (usado) provisto en actividades de operación | C23: =+SUM(C8:C22) -> -3252.55
B25: Flujo de efectivo por actividades de inversión:
B26: Aumento (Disminucion) Reserva legal | C26: =+'HOJA DE TRABAJO'!F31 -> 0
B27: Disminucion de activos fijos | C27: =+'HOJA DE TRABAJO'!F33 -> 0
B28: Adquisición de activos fijos | C28: =+'HOJA DE TRABAJO'!F28 -> 0 | D28: <----------------------- | F28: Al adquirir activo fijo representa una salida de efectivo que en el Estado de Resultado no se encuentra ya que se compensa en la depreciacion mensual
B29: Efectivo neto (usado) en actividades de inversión | C29: =+SUM(C25:C28) -> 0
B31: Flujo de efectivo por actividades Financieras
B32: Efectivo utilizado en actividades de Financiamiento
B33: Efectivo neto (usado) en actividades de inversión | C33: =+SUM(C32) -> 0
B35: (Disminución) aumento en el efectivo | C35: =+C23+C29 -> -3252.55 | D35: <----------------------- | F35: Uso del efectivo en el periodo 2025 en diferentes actividades
B36: Efectivo al inicio del periodo | C36: 4834.34 | D36: <----------------------- | F36: El Efectivo al inicio del periodo lo afectamo con lo del periodo 2025
B37: Efectivo al final del periodo | C37: =+SUM(C35:C36) -> 1581.79 | D37: <----------------------- | F37: Este es el efectivo al final del periodo
B41: ________________________________ _____________________________________
B42: GABRIEL PERDOMO RODAS LIC. RONNY ALEXIS CHAVEZ SANTOS
B43: Representante Legal Contador General
B46: _______________________________________
B47: LIC. JUAN CARLOS MIRA JORGE | G47: 1581.79 | H47: =+C37-G47 -> -2.7284841e-12
B48: AUDITOR EXTERNO
B49: No REG. 4766

Sheet HOJA DE TRABAJO
B2: Variaciones
B3: 2025 | D3: 2024
A5: depre | B5: 1945.2 | D5: 1945.2 | F5: =+B5-D5 -> 0
A7: Cuentas por cobrar | B7: 75267.09 | D7: 75988.28 | F7: =+D7-B7 -> 721.19
A9: Inventario | B9: 0 | D9: 0 | F9: =+D9-B9 -> 0
A11: Pagos anticipado | B11: 1589.22 | D11: 1434.35 | F11: =+D11-B11 -> -154.87
A13: Iva credito | B13: 1630.7 | D13: 2398.7 | F13: =+D13-B13 -> 768
A15: cuentas por pagar y gastos acumulados | B15: 75000 | D15: 76091.6 | F15: =+B15-D15 -> -1091.6
A16: Proveedores Locales
A18: Aumento (disminución) en Deuda Financiera a L.P. | B18: 0 | D18: 0 | F18: =+B18-D18 -> 0
A20: Disminución (aumento) en otras cuentas por pagar | B20: 0 | D20: 0 | F20: =+B20-D20 -> 0
A22: Retenciones por pagar | B22: 487.51 | D22: 589.55 | F22: =+B22-D22 -> -102.04
A24: Impuesto por pagar | B24: 154.87 | D24: 0 | F24: =+B24-D24 -> 154.87
A26: Obligaciones a Corto Plazo | B26: 0 | D26: 0 | F26: =+B26-D26 -> 0
A28: Adquisición de activos fijos | B28: 1945.2 | D28: 1945.2 | F28: =+D28-B28 -> 0
A29: Propiedad, Planta y Equipo
A31: Reserva Legal | B31: 400 | D31: 400 | F31: =+B31-D31 -> 0
A33: Disminucion en activo fijo | B33: 0 | D33: 0 | F33: =+D33-B33 -> 0
F35: =+'Flujo 2025'!C8 -> -3548.1

Sheet FE 2017-2016
B1: BENGALA AUDIOVISUAL, S.A. DE C.V. | F1: Estado Flujo de Efectivo
B2: Estados de Flujos de Efectivo | F2: Informa sobre los movimientos de efectivo y sus equivalentes
B3: Del 1 enero al 31 de Diciembre de 2017 Y 2016
B4: (Valores expresados en dólares de los Estados Unidos de Norte América)
C6: 2017 | D6: 2016
B7: Flujo de efectivo por actividades de operación:
B8: Excedente (Deficit) de ingresos sobre Ejercicio 2017 | C8: -3966.08 | D8: -3062.39 | F8: <--- | G8: Inicia con lo que refleja el Estado de Resultado
B9: Ajustes para conciliar el excedente de ingresos sobre gastos, con el efectivo neto provisto por las operaciones:
B10: Depreciación | C10: =+'HOJA DE TRABAJO'!F5 -> 0 | D10: 0 | F10: <--- | G10: Le sumamos el incremento de la depreciacion al resultado porque este no representa salida de dinero
B11: Retiro neto de activos
B12: Movimiento en el capital de trabajo:
B13: Disminución (aumento) en cuentas por cobrar | C13: =+'HOJA DE TRABAJO'!F7 -> 721.19 | D13: 0
B14: Disminución (aumento) en inventario | C14: =+'HOJA DE TRABAJO'!F9 -> 0 | D14: 0
B15: Disminución (aumento) pagos anticipados | C15: =+'HOJA DE TRABAJO'!F11 -> -154.87 | D15: 0
B16: Disminución (aumento) Iva Credito | C16: =+'HOJA DE TRABAJO'!F13 -> 768 | D16: 0
B17: Aumento (disminución) en cuentas por pagar y gastos acumulados | C17: =+'HOJA DE TRABAJO'!F15 -> -1091.6 | D17: 0 | G17: Le sumamos aquello que no representa salida dinero de efectivo
B18: Aumento (disminución) en en Deuda Financiera a L.P. | C18: =+'HOJA DE TRABAJO'!F18 -> 0 | D18: 0 | G18: Restamos aquello que si representa salida de efectivo
B19: Disminución (aumento) en obligaciones a corto plazo | C19: =+'HOJA DE TRABAJO'!F20 -> 0 | D19: 0 | G19: Estas cuentas afectaron los resultados de septiembre 2014
B20: Disminución (aumento) en Retenciones por pagar | C20: =+'HOJA DE TRABAJO'!F22 -> -102.04 | D20: 0
B21: Aumento (disminución) Impuesto por pagar | C21: =+'HOJA DE TRABAJO'!F24 -> 154.87 | D21: 0
B22: Obligaciones a Corto Plazo | C22: =+'HOJA DE TRABAJO'!F26 -> 0 | D22: 0
B23: Efectivo neto (usado) provisto en actividades de operación | C23: =+SUM(C8:C22) -> -3670.53 | D23: =+SUM(D8:D22) -> -3062.39
B25: Flujo de efectivo por actividades de inversión:
B26: Aumento (Disminucion) Reserva legal | C26: =+'HOJA DE TRABAJO'!F31 -> 0 | D26: 0
B27: Adquisición de activos fijos | C27: =+'HOJA DE TRABAJO'!F28 -> 0 | D27: 0 | E27: <----------------------- | G27: Al adquirir activo fijo representa una salida de efectivo que en el Estado de Resultado no se encuentra ya que se compensa en la depreciacion mensual
B28: Efectivo neto (usado) en actividades de inversión | C28: =+SUM(C25:C27) -> 0 | D28: =+SUM(D25:D27) -> 0
B30: Flujo de efectivo por actividades Financieras
B31: Efectivo utilizado en actividades de Financiamiento
B32: Efectivo neto (usado) en actividades de inversión | C32: =+SUM(C31) -> 0 | D32: =+SUM(D31) -> 0
B34: (Disminución) aumento en el efectivo | C34: =+C23+C28 -> -3670.53 | D34: =+D23+D28 -> -3062.39 | E34: <----------------------- | G34: Uso del efectivo en el periodo 2014 en diferentes actividades
B35: Efectivo al inicio del periodo | C35: 1775.29 | D35: 6468.02 | E35: <----------------------- | G35: El Efectivo al inicio del periodo lo afectamo con lo del periodo 2014
B36: Efectivo al final del periodo | C36: =+SUM(C34:C35) -> -1895.24 | D36: =+SUM(D34:D35) -> 3405.63 | E36: <----------------------- | G36: Este es el efectivo al final del periodo
B40: ________________________________ _____________________________________
B41: GUSTAVO ADOLFO PERDOMO RODAS LIC. RONNY ALEXIS CHAVEZ SANTOS
B42: Representante Legal Contador General
B45: _______________________________________
B46: LIC. JUAN CARLOS MIRA JORGE
B47: AUDITOR EXTERNO
B48: No REG. 4766

Sheet Hoja3
